singa.libs/libz-d8a329de.so.1.2.7
singa.libs/libgomp-7c85b1e2.so.1.0.0
singa.libs/libopenblas-r0-f650aae0.3.3.so
singa.libs/libquadmath-30d679e1.so.0.0.0
singa.libs/libprotobuf-cb0440da.so.8.0.0
singa.libs/libdnnl-034bb581.so.1
singa.libs/libglog-28eec8ed.so.0.0.0
singa.libs/libgfortran-4fc760a1.so.3.0.0
singa/device.py
singa/autograd.py
singa/model.py
singa/data.py
singa/_singa_wrap.cpython-36m-x86_64-linux-gnu.so
singa/metric.py
singa/optimizer.py
singa/singa_wrap.py
singa/opt.py
singa/initializer.py
singa/image_tool.py
singa/snapshot.py
singa/tensor.py
singa/utils.py
singa/__init__.py
singa/sonnx.py
singa/layer.py
singa/loss.py
singa-3.0.0.dev1.dist-info/top_level.txt
singa-3.0.0.dev1.dist-info/WHEEL
singa-3.0.0.dev1.dist-info/RECORD
singa-3.0.0.dev1.dist-info/METADATA
singa-3.0.0.dev1.dist-info/LICENSE
singa-3.0.0.dev1.dist-info/NOTICE
