Metadata-Version: 2.1
Name: singa
Version: 3.0.0.dev1
Summary: A General Deep Learning System
Home-page: http://singa.apache.org
Author: Apache SINGA Community
Author-email: dev@singa.apache.org
License: Apache 2
Keywords: deep learning singa apache
Platform: UNKNOWN
Classifier: License :: OSI Approved :: Apache Software License
Classifier: Development Status :: 3 - Alpha
Classifier: Intended Audience :: Developers
Classifier: Programming Language :: Python :: 3.6
Classifier: Programming Language :: Python :: 3.7
Classifier: Programming Language :: Python :: 3.8
Classifier: Topic :: Scientific/Engineering :: Artificial Intelligence
Requires-Python: >=3
Requires-Dist: numpy (<2.0,>=1.16)
Requires-Dist: onnx (==1.6)
Requires-Dist: deprecated
Requires-Dist: unittest-xml-reporting
Requires-Dist: future
Requires-Dist: pillow
Requires-Dist: tqdm
